{
  "cards": [
    {
      "name": "Action Card 1",
      "description": "A Technology action",
      "category": "Technology",
      "responsibility": 0,
      "effect": 3
    },
    {
      "name": "Action Card 2",
      "description": "A Governance action",
      "category": "Governance",
      "responsibility": 2,
      "effect": 3
    },
    {
      "name": "Action Card 3",
      "description": "A Technology action",
      "category": "Technology",
      "responsibility": 2,
      "effect": 3
    },
    {
      "name": "Action Card 4",
      "description": "A Governance action",
      "category": "Governance",
      "responsibility": 0,
      "effect": 2
    },
    {
      "name": "Action Card 5",
      "description": "A Technology action",
      "category": "Technology",
      "responsibility": 3,
      "effect": 3
    },
    {
      "name": "Action Card 6",
      "description": "A Governance action",
      "category": "Governance",
      "responsibility": 1,
      "effect": 3
    },
    {
      "name": "Action Card 7",
      "description": "A Technology action",
      "category": "Technology",
      "responsibility": 1,
      "effect": 1
    },
    {
      "name": "Action Card 8",
      "description": "A Technology action",
      "category": "Technology",
      "responsibility": 0,
      "effect": 2
    },
    {
      "name": "Action Card 9",
      "description": "A Intelligence action",
      "category": "Intelligence",
      "responsibility": 1,
      "effect": 2
    },
    {
      "name": "Action Card 10",
      "description": "A Cybersecurity action",
      "category": "Cybersecurity",
      "responsibility": 1,
      "effect": 1
    },
    {
      "name": "Action Card 11",
      "description": "A Cybersecurity action",
      "category": "Cybersecurity",
      "responsibility": 1,
      "effect": 3
    },
    {
      "name": "Action Card 12",
      "description": "A Intelligence action",
      "category": "Intelligence",
      "responsibility": 0,
      "effect": 2
    },
    {
      "name": "Action Card 13",
      "description": "A Intelligence action",
      "category": "Intelligence",
      "responsibility": 0,
      "effect": 2
    },
    {
      "name": "Action Card 14",
      "description": "A Governance action",
      "category": "Governance",
      "responsibility": 3,
      "effect": 2
    },
    {
      "name": "Action Card 15",
      "description": "A Governance action",
      "category": "Governance",
      "responsibility": 3,
      "effect": 4
    },
    {
      "name": "Action Card 16",
      "description": "A Governance action",
      "category": "Governance",
      "responsibility": 0,
      "effect": 4
    },
    {
      "name": "Action Card 17",
      "description": "A Technology action",
      "category": "Technology",
      "responsibility": 1,
      "effect": 3
    },
    {
      "name": "Action Card 18",
      "description": "A Cybersecurity action",
      "category": "Cybersecurity",
      "responsibility": 3,
      "effect": 3
    },
    {
      "name": "Action Card 19",
      "description": "A Technology action",
      "category": "Technology",
      "responsibility": 1,
      "effect": 4
    },
    {
      "name": "Action Card 20",
      "description": "A Intelligence action",
      "category": "Intelligence",
      "responsibility": 3,
      "effect": 4
    },
    {
      "name": "Action Card 21",
      "description": "A Governance action",
      "category": "Governance",
      "responsibility": 2,
      "effect": 3
    },
    {
      "name": "Action Card 22",
      "description": "A Cybersecurity action",
      "category": "Cybersecurity",
      "responsibility": 3,
      "effect": 2
    },
    {
      "name": "Action Card 23",
      "description": "A Cybersecurity action",
      "category": "Cybersecurity",
      "responsibility": 0,
      "effect": 2
    },
    {
      "name": "Action Card 24",
      "description": "A Cybersecurity action",
      "category": "Cybersecurity",
      "responsibility": 0,
      "effect": 3
    },
    {
      "name": "Action Card 25",
      "description": "A Governance action",
      "category": "Governance",
      "responsibility": 0,
      "effect": 3
    },
    {
      "name": "Action Card 26",
      "description": "A Cybersecurity action",
      "category": "Cybersecurity",
      "responsibility": 3,
      "effect": 4
    },
    {
      "name": "Action Card 27",
      "description": "A Governance action",
      "category": "Governance",
      "responsibility": 2,
      "effect": 1
    },
    {
      "name": "Action Card 28",
      "description": "A Cybersecurity action",
      "category": "Cybersecurity",
      "responsibility": 3,
      "effect": 1
    },
    {
      "name": "Action Card 29",
      "description": "A Intelligence action",
      "category": "Intelligence",
      "responsibility": 2,
      "effect": 4
    },
    {
      "name": "Action Card 30",
      "description": "A Technology action",
      "category": "Technology",
      "responsibility": 2,
      "effect": 3
    },
    {
      "name": "Action Card 31",
      "description": "A Cybersecurity action",
      "category": "Cybersecurity",
      "responsibility": 1,
      "effect": 1
    },
    {
      "name": "Action Card 32",
      "description": "A Technology action",
      "category": "Technology",
      "responsibility": 2,
      "effect": 2
    },
    {
      "name": "Action Card 33",
      "description": "A Governance action",
      "category": "Governance",
      "responsibility": 1,
      "effect": 4
    },
    {
      "name": "Action Card 34",
      "description": "A Intelligence action",
      "category": "Intelligence",
      "responsibility": 0,
      "effect": 4
    },
    {
      "name": "Action Card 35",
      "description": "A Cybersecurity action",
      "category": "Cybersecurity",
      "responsibility": 2,
      "effect": 2
    },
    {
      "name": "Action Card 36",
      "description": "A Technology action",
      "category": "Technology",
      "responsibility": 0,
      "effect": 2
    }
  ]
}